setup.py
vodafone_scraper/__init__.py
vodafone_scraper/main.py
vodafone_scraper.egg-info/PKG-INFO
vodafone_scraper.egg-info/SOURCES.txt
vodafone_scraper.egg-info/dependency_links.txt
vodafone_scraper.egg-info/entry_points.txt
vodafone_scraper.egg-info/namespace_packages.txt
vodafone_scraper.egg-info/not-zip-safe
vodafone_scraper.egg-info/requires.txt
vodafone_scraper.egg-info/top_level.txt