Metadata-Version: 1.1
Name: vodafone-scraper
Version: 1.0.0
Summary: Scrapes your current usage information from the MyVodafone website.
Home-page: http://paulfurley.com
Author: Paul M Furley
Author-email: paul@paulfurley.com
License: MIT
Platform: UNKNOWN
Classifier: Development Status :: 5 - Production/Stable
Classifier: Intended Audience :: Developers
Classifier: Intended Audience :: End Users/Desktop
Classifier: License :: OSI Approved :: MIT License
Classifier: Operating System :: POSIX :: Linux
Classifier: Programming Language :: Python
